vdw/__init__.py
vdw/modeldftd3.py
vdw/modeldftd4.py
vdw/modelmbd.py
vdw/modeltsvdw_deprecated.py
vdw/wrapper.py
vdw/util/__init__.py
vdw/util/hirshfeld.py
vdw/util/sph_dft_atom_ks.py
vdw/util/sph_dft_elements.py
vdw/util/vdw_param.py
pyvdw-0.1.0.dist-info/LICENSE
pyvdw-0.1.0.dist-info/METADATA
pyvdw-0.1.0.dist-info/WHEEL
pyvdw-0.1.0.dist-info/top_level.txt
pyvdw-0.1.0.dist-info/RECORD
