Metadata-Version: 2.1
Name: pyvdw
Version: 0.1.0
Summary: My wrapper of various existing vDW libraries for PySCF
Home-page: https://github.com/ajz34/vdw
Author: ajz34
Author-email: ajz34@outlook.com
License: UNKNOWN
Platform: UNKNOWN
Classifier: Programming Language :: Python :: 3
Classifier: License :: OSI Approved :: Apache Software License
Classifier: Operating System :: POSIX :: Linux
License-File: LICENSE
Requires-Dist: numpy
Requires-Dist: pyscf
